keyfree/__init__.py
keyfree/auth.py
keyfree/proxy.py
keyfree/version.py
keyfree/test/__init__.py
keyfree/test/test_auth.py
keyfree/test/test_proxy.py
keyfree/test/util.py
keyfree-1.0.0.dist-info/DESCRIPTION.rst
keyfree-1.0.0.dist-info/METADATA
keyfree-1.0.0.dist-info/RECORD
keyfree-1.0.0.dist-info/WHEEL
keyfree-1.0.0.dist-info/entry_points.txt
keyfree-1.0.0.dist-info/metadata.json
keyfree-1.0.0.dist-info/top_level.txt
