Metadata-Version: 2.0
Name: keyfree
Version: 1.0.0
Summary: An authentication proxy for Amazon Elasticsearch Service
Home-page: https://github.com/nickrw/keyfree
Author: Nicholas Robinson-Wall
Author-email: nick@robinson-wall.com
License: MIT
Platform: UNKNOWN
Classifier: Development Status :: 4 - Beta
Classifier: License :: OSI Approved :: MIT License
Classifier: Intended Audience :: System Administrators
Classifier: Intended Audience :: Developers
Classifier: Programming Language :: Python :: 2
Classifier: Programming Language :: Python :: 3
Classifier: Environment :: No Input/Output (Daemon)
Classifier: Topic :: Internet :: Proxy Servers
Classifier: Topic :: Internet :: WWW/HTTP :: Indexing/Search
Classifier: Topic :: Internet :: WWW/HTTP :: WSGI :: Middleware
Requires-Dist: boto3 (==1.4.1)
Requires-Dist: flask (==0.11.1)
Requires-Dist: requests (==2.11.1)
Requires-Dist: requests-aws4auth (==0.9)
